{
  "hash": "455214e2",
  "configHash": "410d9b45",
  "lockfileHash": "501e3f08",
  "browserHash": "3fcdfc27",
  "optimized": {
    "@gsap/react": {
      "src": "../../node_modules/@gsap/react/src/index.js",
      "file": "@gsap_react.js",
      "fileHash": "88210b5c",
      "needsInterop": false
    },
    "gsap": {
      "src": "../../node_modules/gsap/index.js",
      "file": "gsap.js",
      "fileHash": "6dbed3fc",
      "needsInterop": false
    },
    "gsap/ScrollTrigger": {
      "src": "../../node_modules/gsap/ScrollTrigger.js",
      "file": "gsap_ScrollTrigger.js",
      "fileHash": "0c393fa6",
      "needsInterop": false
    },
    "react": {
      "src": "../../node_modules/react/index.js",
      "file": "react.js",
      "fileHash": "16ec81bf",
      "needsInterop": true
    },
    "react-dom/client": {
      "src": "../../node_modules/react-dom/client.js",
      "file": "react-dom_client.js",
      "fileHash": "4af4ed1d",
      "needsInterop": true
    },
    "react-router-dom": {
      "src": "../../node_modules/react-router-dom/dist/index.mjs",
      "file": "react-router-dom.js",
      "fileHash": "28d658d7",
      "needsInterop": false
    }
  },
  "chunks": {
    "chunk-PLLKX35O": {
      "file": "chunk-PLLKX35O.js"
    },
    "chunk-DBUGNT2R": {
      "file": "chunk-DBUGNT2R.js"
    },
    "chunk-VUPZMC2T": {
      "file": "chunk-VUPZMC2T.js"
    },
    "chunk-EQCVQC35": {
      "file": "chunk-EQCVQC35.js"
    }
  }
}